{
    "Name": "Fires of Invention",
    "IncludeColorInName": false,
    "Conditions": [
        {
            "Type": "InMainboard",
            "Cards": ["Fires of Invention"]
        },
        {
          "Type": "DoesNotContainSideboard",
          "Cards": ["Keruga, the Macrosage"]
        }
    ],
    "Variants": [
      {
        "Name": "Enigmatic Incarnation",
        "IncludeColorInName": true,
        "Conditions": [
          {
            "Type": "InMainboard",
            "Cards": ["Enigmatic Incarnation"]
          }
          ]
  
      }
    ]
  }