{
  "Name": "Omni-Tell",
  "IncludeColorInName": false,
  "Conditions": [
    {
      "Type": "InMainboard",
      "Cards": ["Show and Tell"]
    },
    {
      "Type": "InMainboard",
      "Cards": ["Omniscience"]
    }
  ],
  "Variants": [
    {
      "Name": "Hypergenesis",
      "IncludeColorInName": false,
      "Conditions": [
        {
          "Type": "InMainboard",
          "Cards": ["Hypergenesis"]
        }
      ]
    },
    {
      "Name": "Creative technique",
      "IncludeColorInName": false,
      "Conditions": [
        {
          "Type": "InMainboard",
          "Cards": ["Creative Technique"]
        }
      ]
    }
  ]
}
